camphr_allennlp/VERSION.py
camphr_allennlp/__init__.py
camphr_allennlp/allennlp_base.py
camphr_allennlp/elmo.py
camphr_allennlp/udify.py
camphr_allennlp-0.1.3.dist-info/entry_points.txt
camphr_allennlp-0.1.3.dist-info/WHEEL
camphr_allennlp-0.1.3.dist-info/METADATA
camphr_allennlp-0.1.3.dist-info/RECORD
