Metadata-Version: 2.1
Name: camphr-allennlp
Version: 0.1.3
Summary: AllenNLP plugin for camphr
Home-page: https://github.com/PKSHATechnology-Research/camphr-allennlp
License: Apache-2.0
Keywords: spaCy,nlp,natural language processing,udify,allennlp
Author: Yohei Tamura
Author-email: tamuhey@gmail.com
Requires-Python: >=3.6.1
Classifier: License :: OSI Approved :: Apache Software License
Classifier: Programming Language :: Python :: 3
Classifier: Programming Language :: Python :: 3.7
Classifier: Programming Language :: Python :: 3.8
Classifier: Programming Language :: Python :: 3.9
Requires-Dist: allennlp (>=1.0.0,<=1.0.1)
Requires-Dist: boto3 (>=1.14.44,<2.0.0)
Requires-Dist: camphr (>=0.7.0,<0.8)
Requires-Dist: unofficial-udify (==0.2.1)
Project-URL: Repository, https://github.com/PKSHATechnology-Research/camphr-allennlp
